echo_mcp_server_for_testing/__init__.py
echo_mcp_server_for_testing/main.py
mseep_echo_mcp_server_for_testing-1.0.0.dist-info/licenses/LICENSE
mseep_echo_mcp_server_for_testing-1.0.0.dist-info/METADATA
mseep_echo_mcp_server_for_testing-1.0.0.dist-info/WHEEL
mseep_echo_mcp_server_for_testing-1.0.0.dist-info/top_level.txt
mseep_echo_mcp_server_for_testing-1.0.0.dist-info/RECORD
